analyzere/__init__.py
analyzere/base_resources.py
analyzere/errors.py
analyzere/requestor.py
analyzere/resources.py
analyzere/utils.py
analyzere-0.9.dist-info/LICENSE
analyzere-0.9.dist-info/METADATA
analyzere-0.9.dist-info/WHEEL
analyzere-0.9.dist-info/RECORD
