Metadata-Version: 2.1
Name: analyzere
Version: 0.9
Summary: 
Author: Developers
Author-email: dev@analyzere.com
Requires-Python: >=3.8,<4.0
Classifier: Programming Language :: Python :: 3
Classifier: Programming Language :: Python :: 3.8
Classifier: Programming Language :: Python :: 3.9
Classifier: Programming Language :: Python :: 3.10
Classifier: Programming Language :: Python :: 3.11
Requires-Dist: lazy-object-proxy (>=1.9.0,<2.0.0)
Requires-Dist: requests (>=2.31.0,<3.0.0)
Requires-Dist: requests-oauthlib (>=2.0.0,<3.0.0)
Requires-Dist: six (>=1.16.0,<2.0.0)
